.travis.yml
AUTHORS
ChangeLog
LICENCE.txt
Makefile
README.rst
requirements.txt
setup.cfg
setup.py
registryctl/__init__.py
registryctl/cli.py
registryctl.egg-info/PKG-INFO
registryctl.egg-info/SOURCES.txt
registryctl.egg-info/dependency_links.txt
registryctl.egg-info/entry_points.txt
registryctl.egg-info/not-zip-safe
registryctl.egg-info/pbr.json
registryctl.egg-info/requires.txt
registryctl.egg-info/top_level.txt
registryctl/blobs/__init__.py
registryctl/catalog/__init__.py
registryctl/catalog/client.py
registryctl/catalog/resources.py
registryctl/common/__init__.py
registryctl/common/authclient.py
registryctl/common/commandmanager.py
registryctl/common/exceptions.py
registryctl/common/utils.py