Metadata-Version: 1.1
Name: registryctl
Version: 0.2.0
Summary: Docker Registry CLI
Home-page: https://github.com/Flav35/registryctl
Author: Flavien Hardy
Author-email: flav.hardy@gmail.com
License: UNKNOWN
Platform: UNKNOWN
Classifier: Programming Language :: Python :: 2
Classifier: Programming Language :: Python :: 2.7
Classifier: Programming Language :: Python :: 3
Classifier: Programming Language :: Python :: 3.5
